CHANGELOG.md
LICENSE
MANIFEST.in
Makefile
README.md
setup.cfg
setup.py
tox.ini
tests/test_resolvement.py
tests/test_setters.py
tests/test_views.py
wc_django_settings.egg-info/PKG-INFO
wc_django_settings.egg-info/SOURCES.txt
wc_django_settings.egg-info/dependency_links.txt
wc_django_settings.egg-info/requires.txt
wc_django_settings.egg-info/top_level.txt
wcd_settings/__init__.py
wcd_settings/admin.py
wcd_settings/apps.py
wcd_settings/middleware.py
wcd_settings/models.py
wcd_settings/registries.py
wcd_settings/resolvers.py
wcd_settings/setters.py
wcd_settings/shortcuts.py
wcd_settings/views.py
wcd_settings/locale/af/LC_MESSAGES/django.mo
wcd_settings/locale/af/LC_MESSAGES/django.po
wcd_settings/locale/ar/LC_MESSAGES/django.mo
wcd_settings/locale/ar/LC_MESSAGES/django.po
wcd_settings/locale/ast/LC_MESSAGES/django.mo
wcd_settings/locale/ast/LC_MESSAGES/django.po
wcd_settings/locale/az/LC_MESSAGES/django.mo
wcd_settings/locale/az/LC_MESSAGES/django.po
wcd_settings/locale/be/LC_MESSAGES/django.mo
wcd_settings/locale/be/LC_MESSAGES/django.po
wcd_settings/locale/bg/LC_MESSAGES/django.mo
wcd_settings/locale/bg/LC_MESSAGES/django.po
wcd_settings/locale/bn/LC_MESSAGES/django.mo
wcd_settings/locale/bn/LC_MESSAGES/django.po
wcd_settings/locale/br/LC_MESSAGES/django.mo
wcd_settings/locale/br/LC_MESSAGES/django.po
wcd_settings/locale/bs/LC_MESSAGES/django.mo
wcd_settings/locale/bs/LC_MESSAGES/django.po
wcd_settings/locale/ca/LC_MESSAGES/django.mo
wcd_settings/locale/ca/LC_MESSAGES/django.po
wcd_settings/locale/cs/LC_MESSAGES/django.mo
wcd_settings/locale/cs/LC_MESSAGES/django.po
wcd_settings/locale/cy/LC_MESSAGES/django.mo
wcd_settings/locale/cy/LC_MESSAGES/django.po
wcd_settings/locale/da/LC_MESSAGES/django.mo
wcd_settings/locale/da/LC_MESSAGES/django.po
wcd_settings/locale/de/LC_MESSAGES/django.mo
wcd_settings/locale/de/LC_MESSAGES/django.po
wcd_settings/locale/dsb/LC_MESSAGES/django.mo
wcd_settings/locale/dsb/LC_MESSAGES/django.po
wcd_settings/locale/el/LC_MESSAGES/django.mo
wcd_settings/locale/el/LC_MESSAGES/django.po
wcd_settings/locale/en/LC_MESSAGES/django.mo
wcd_settings/locale/en/LC_MESSAGES/django.po
wcd_settings/locale/eo/LC_MESSAGES/django.mo
